TimeSeriesAnalysisPlugin/__init__.py
TimeSeriesAnalysisPlugin/common/__init__.py
TimeSeriesAnalysisPlugin/common/local_plugin_service.py
TimeSeriesAnalysisPlugin/common/plugin_model_api.py
TimeSeriesAnalysisPlugin/common/plugin_service.py
TimeSeriesAnalysisPlugin/common/tsanaclient.py
TimeSeriesAnalysisPlugin/common/util/__init__.py
TimeSeriesAnalysisPlugin/common/util/azureblob.py
TimeSeriesAnalysisPlugin/common/util/azuretable.py
TimeSeriesAnalysisPlugin/common/util/constant.py
TimeSeriesAnalysisPlugin/common/util/csv.py
TimeSeriesAnalysisPlugin/common/util/data.py
TimeSeriesAnalysisPlugin/common/util/gran.py
TimeSeriesAnalysisPlugin/common/util/meta.py
TimeSeriesAnalysisPlugin/common/util/model.py
TimeSeriesAnalysisPlugin/common/util/monitor.py
TimeSeriesAnalysisPlugin/common/util/retryrequests.py
TimeSeriesAnalysisPlugin/common/util/series.py
TimeSeriesAnalysisPlugin/common/util/timeutil.py
TimeSeriesAnalysisPlugin/correlation/__init__.py
TimeSeriesAnalysisPlugin/correlation/correlation_plugin_service.py
TimeSeriesAnalysisPlugin/correlation/correlation_test.py
TimeSeriesAnalysisPlugin/correlation/run_server.py
TimeSeriesAnalysisPlugin/custom_detector/__init__.py
TimeSeriesAnalysisPlugin/custom_detector/custom_detector_plugin_service.py
TimeSeriesAnalysisPlugin/custom_detector/run_server.py
TimeSeriesAnalysisPlugin/forecast/__init__.py
TimeSeriesAnalysisPlugin/forecast/forecast_plugin_service.py
TimeSeriesAnalysisPlugin/forecast/run_server.py
TimeSeriesAnalysisPlugin/maga/__init__.py
TimeSeriesAnalysisPlugin/maga/maga_plugin_service.py
TimeSeriesAnalysisPlugin/maga/magaclient.py
TimeSeriesAnalysisPlugin/maga/run_server.py
time_series_analysis_plugin-0.0.1.dist-info/METADATA
time_series_analysis_plugin-0.0.1.dist-info/WHEEL
time_series_analysis_plugin-0.0.1.dist-info/top_level.txt
time_series_analysis_plugin-0.0.1.dist-info/RECORD
